autoquant/__init__.py
autoquant/config.py
autoquant/log.py
autoquant/action/__init__.py
autoquant/broker/__init__.py
autoquant/collector/__init__.py
autoquant/indicator/__init__.py
autoquant/metric/__init__.py
autoquant/mixin/__init__.py
autoquant/mixin/data.py
autoquant/model/__init__.py
autoquant/provider/__init__.py
autoquant/provider/baostock.py
autoquant/provider/eastmoney.py
autoquant/provider/snowball.py
autoquant/provider/tushare.py
autoquant/strategy/__init__.py
autoquant/workflow/__init__.py
AutoQuant-1.1.1.dist-info/LICENSE
AutoQuant-1.1.1.dist-info/METADATA
AutoQuant-1.1.1.dist-info/WHEEL
AutoQuant-1.1.1.dist-info/top_level.txt
AutoQuant-1.1.1.dist-info/RECORD
