Metadata-Version: 2.1
Name: AutoQuant
Version: 1.1.1
Summary: Auto Quant
Home-page: https://github.com/marcnuth/AutoQuant
Author: NAUTIDEA
Author-email: xian@nautidea.com
Project-URL: Bug Tracker, https://github.com/marcnuth/AutoQuant/issues
Classifier: Programming Language :: Python :: 3
Classifier: Topic :: Scientific/Engineering :: Artificial Intelligence
Classifier: Topic :: Software Development :: Libraries
Classifier: Operating System :: POSIX :: Linux
Classifier: Operating System :: Microsoft :: Windows
Classifier: Operating System :: MacOS
Classifier: Operating System :: OS Independent
Requires-Python: >=3.6
License-File: LICENSE
